{
  "openapi": "3.0.4",
  "info": {
    "title": "IglesiaAPI",
    "version": "1.0"
  },
  "paths": {
    "/api/Auth/login": {
      "post": {
        "tags": [
          "Auth"
        ],
        "requestBody": {
          "content": {
            "application/json": {
              "schema": {
                "$ref": "#/components/schemas/LoginRequest"
              }
            },
            "text/json": {
              "schema": {
                "$ref": "#/components/schemas/LoginRequest"
              }
            },
            "application/*+json": {
              "schema": {
                "$ref": "#/components/schemas/LoginRequest"
              }
            }
          }
        },
        "responses": {
          "200": {
            "description": "OK"
          }
        }
      }
    },
    "/api/Celulas": {
      "get": {
        "tags": [
          "Celulas"
        ],
        "responses": {
          "200": {
            "description": "OK",
            "content": {
              "text/plain": {
                "schema": {
                  "type": "array",
                  "items": {
                    "$ref": "#/components/schemas/Celula"
                  }
                }
              },
              "application/json": {
                "schema": {
                  "type": "array",
                  "items": {
                    "$ref": "#/components/schemas/Celula"
                  }
                }
              },
              "text/json": {
                "schema": {
                  "type": "array",
                  "items": {
                    "$ref": "#/components/schemas/Celula"
                  }
                }
              }
            }
          }
        }
      },
      "post": {
        "tags": [
          "Celulas"
        ],
        "requestBody": {
          "content": {
            "application/json": {
              "schema": {
                "$ref": "#/components/schemas/CelulaDTO"
              }
            },
            "text/json": {
              "schema": {
                "$ref": "#/components/schemas/CelulaDTO"
              }
            },
            "application/*+json": {
              "schema": {
                "$ref": "#/components/schemas/CelulaDTO"
              }
            }
          }
        },
        "responses": {
          "200": {
            "description": "OK",
            "content": {
              "text/plain": {
                "schema": {
                  "$ref": "#/components/schemas/Celula"
                }
              },
              "application/json": {
                "schema": {
                  "$ref": "#/components/schemas/Celula"
                }
              },
              "text/json": {
                "schema": {
                  "$ref": "#/components/schemas/Celula"
                }
              }
            }
          }
        }
      }
    },
    "/api/Celulas/{id}": {
      "get": {
        "tags": [
          "Celulas"
        ],
        "parameters": [
          {
            "name": "id",
            "in": "path",
            "required": true,
            "schema": {
              "type": "integer",
              "format": "int32"
            }
          }
        ],
        "responses": {
          "200": {
            "description": "OK",
            "content": {
              "text/plain": {
                "schema": {
                  "$ref": "#/components/schemas/Celula"
                }
              },
              "application/json": {
                "schema": {
                  "$ref": "#/components/schemas/Celula"
                }
              },
              "text/json": {
                "schema": {
                  "$ref": "#/components/schemas/Celula"
                }
              }
            }
          }
        }
      },
      "put": {
        "tags": [
          "Celulas"
        ],
        "parameters": [
          {
            "name": "id",
            "in": "path",
            "required": true,
            "schema": {
              "type": "integer",
              "format": "int32"
            }
          }
        ],
        "requestBody": {
          "content": {
            "application/json": {
              "schema": {
                "$ref": "#/components/schemas/CelulaDTO"
              }
            },
            "text/json": {
              "schema": {
                "$ref": "#/components/schemas/CelulaDTO"
              }
            },
            "application/*+json": {
              "schema": {
                "$ref": "#/components/schemas/CelulaDTO"
              }
            }
          }
        },
        "responses": {
          "200": {
            "description": "OK"
          }
        }
      },
      "delete": {
        "tags": [
          "Celulas"
        ],
        "parameters": [
          {
            "name": "id",
            "in": "path",
            "required": true,
            "schema": {
              "type": "integer",
              "format": "int32"
            }
          }
        ],
        "responses": {
          "200": {
            "description": "OK"
          }
        }
      }
    },
    "/api/Cuentas": {
      "get": {
        "tags": [
          "Cuentas"
        ],
        "responses": {
          "200": {
            "description": "OK",
            "content": {
              "text/plain": {
                "schema": {
                  "type": "array",
                  "items": {
                    "$ref": "#/components/schemas/Cuenta"
                  }
                }
              },
              "application/json": {
                "schema": {
                  "type": "array",
                  "items": {
                    "$ref": "#/components/schemas/Cuenta"
                  }
                }
              },
              "text/json": {
                "schema": {
                  "type": "array",
                  "items": {
                    "$ref": "#/components/schemas/Cuenta"
                  }
                }
              }
            }
          }
        }
      },
      "post": {
        "tags": [
          "Cuentas"
        ],
        "requestBody": {
          "content": {
            "application/json": {
              "schema": {
                "$ref": "#/components/schemas/CuentaDTO"
              }
            },
            "text/json": {
              "schema": {
                "$ref": "#/components/schemas/CuentaDTO"
              }
            },
            "application/*+json": {
              "schema": {
                "$ref": "#/components/schemas/CuentaDTO"
              }
            }
          }
        },
        "responses": {
          "200": {
            "description": "OK",
            "content": {
              "text/plain": {
                "schema": {
                  "$ref": "#/components/schemas/Cuenta"
                }
              },
              "application/json": {
                "schema": {
                  "$ref": "#/components/schemas/Cuenta"
                }
              },
              "text/json": {
                "schema": {
                  "$ref": "#/components/schemas/Cuenta"
                }
              }
            }
          }
        }
      }
    },
    "/api/Cuentas/{id}": {
      "get": {
        "tags": [
          "Cuentas"
        ],
        "parameters": [
          {
            "name": "id",
            "in": "path",
            "required": true,
            "schema": {
              "type": "integer",
              "format": "int32"
            }
          }
        ],
        "responses": {
          "200": {
            "description": "OK",
            "content": {
              "text/plain": {
                "schema": {
                  "$ref": "#/components/schemas/Cuenta"
                }
              },
              "application/json": {
                "schema": {
                  "$ref": "#/components/schemas/Cuenta"
                }
              },
              "text/json": {
                "schema": {
                  "$ref": "#/components/schemas/Cuenta"
                }
              }
            }
          }
        }
      },
      "put": {
        "tags": [
          "Cuentas"
        ],
        "parameters": [
          {
            "name": "id",
            "in": "path",
            "required": true,
            "schema": {
              "type": "integer",
              "format": "int32"
            }
          }
        ],
        "requestBody": {
          "content": {
            "application/json": {
              "schema": {
                "$ref": "#/components/schemas/CuentaDTO"
              }
            },
            "text/json": {
              "schema": {
                "$ref": "#/components/schemas/CuentaDTO"
              }
            },
            "application/*+json": {
              "schema": {
                "$ref": "#/components/schemas/CuentaDTO"
              }
            }
          }
        },
        "responses": {
          "200": {
            "description": "OK"
          }
        }
      },
      "delete": {
        "tags": [
          "Cuentas"
        ],
        "parameters": [
          {
            "name": "id",
            "in": "path",
            "required": true,
            "schema": {
              "type": "integer",
              "format": "int32"
            }
          }
        ],
        "responses": {
          "200": {
            "description": "OK"
          }
        }
      }
    },
    "/api/Dashboard": {
      "get": {
        "tags": [
          "Dashboard"
        ],
        "parameters": [
          {
            "name": "localidadId",
            "in": "query",
            "schema": {
              "type": "integer",
              "format": "int32"
            }
          }
        ],
        "responses": {
          "200": {
            "description": "OK",
            "content": {
              "text/plain": {
                "schema": {
                  "$ref": "#/components/schemas/DashboardDTO"
                }
              },
              "application/json": {
                "schema": {
                  "$ref": "#/components/schemas/DashboardDTO"
                }
              },
              "text/json": {
                "schema": {
                  "$ref": "#/components/schemas/DashboardDTO"
                }
              }
            }
          }
        }
      }
    },
    "/api/Dashboard/eventos": {
      "get": {
        "tags": [
          "Dashboard"
        ],
        "parameters": [
          {
            "name": "localidadId",
            "in": "query",
            "schema": {
              "type": "integer",
              "format": "int32"
            }
          }
        ],
        "responses": {
          "200": {
            "description": "OK",
            "content": {
              "text/plain": {
                "schema": {
                  "type": "array",
                  "items": {
                    "$ref": "#/components/schemas/EventoImportanteDTO"
                  }
                }
              },
              "application/json": {
                "schema": {
                  "type": "array",
                  "items": {
                    "$ref": "#/components/schemas/EventoImportanteDTO"
                  }
                }
              },
              "text/json": {
                "schema": {
                  "type": "array",
                  "items": {
                    "$ref": "#/components/schemas/EventoImportanteDTO"
                  }
                }
              }
            }
          }
        }
      }
    },
    "/api/Dashboard/tendencias": {
      "get": {
        "tags": [
          "Dashboard"
        ],
        "parameters": [
          {
            "name": "localidadId",
            "in": "query",
            "schema": {
              "type": "integer",
              "format": "int32"
            }
          }
        ],
        "responses": {
          "200": {
            "description": "OK",
            "content": {
              "text/plain": {
                "schema": {
                  "$ref": "#/components/schemas/TendenciaDTO"
                }
              },
              "application/json": {
                "schema": {
                  "$ref": "#/components/schemas/TendenciaDTO"
                }
              },
              "text/json": {
                "schema": {
                  "$ref": "#/components/schemas/TendenciaDTO"
                }
              }
            }
          }
        }
      }
    },
    "/api/Dashboard/actividad": {
      "get": {
        "tags": [
          "Dashboard"
        ],
        "parameters": [
          {
            "name": "localidadId",
            "in": "query",
            "schema": {
              "type": "integer",
              "format": "int32"
            }
          }
        ],
        "responses": {
          "200": {
            "description": "OK",
            "content": {
              "text/plain": {
                "schema": {
                  "type": "array",
                  "items": {
                    "$ref": "#/components/schemas/ActividadDTO"
                  }
                }
              },
              "application/json": {
                "schema": {
                  "type": "array",
                  "items": {
                    "$ref": "#/components/schemas/ActividadDTO"
                  }
                }
              },
              "text/json": {
                "schema": {
                  "type": "array",
                  "items": {
                    "$ref": "#/components/schemas/ActividadDTO"
                  }
                }
              }
            }
          }
        }
      }
    },
    "/api/Inventarios": {
      "get": {
        "tags": [
          "Inventarios"
        ],
        "responses": {
          "200": {
            "description": "OK",
            "content": {
              "text/plain": {
                "schema": {
                  "type": "array",
                  "items": {
                    "$ref": "#/components/schemas/Inventario"
                  }
                }
              },
              "application/json": {
                "schema": {
                  "type": "array",
                  "items": {
                    "$ref": "#/components/schemas/Inventario"
                  }
                }
              },
              "text/json": {
                "schema": {
                  "type": "array",
                  "items": {
                    "$ref": "#/components/schemas/Inventario"
                  }
                }
              }
            }
          }
        }
      },
      "post": {
        "tags": [
          "Inventarios"
        ],
        "requestBody": {
          "content": {
            "application/json": {
              "schema": {
                "$ref": "#/components/schemas/InventarioDTO"
              }
            },
            "text/json": {
              "schema": {
                "$ref": "#/components/schemas/InventarioDTO"
              }
            },
            "application/*+json": {
              "schema": {
                "$ref": "#/components/schemas/InventarioDTO"
              }
            }
          }
        },
        "responses": {
          "200": {
            "description": "OK",
            "content": {
              "text/plain": {
                "schema": {
                  "$ref": "#/components/schemas/Inventario"
                }
              },
              "application/json": {
                "schema": {
                  "$ref": "#/components/schemas/Inventario"
                }
              },
              "text/json": {
                "schema": {
                  "$ref": "#/components/schemas/Inventario"
                }
              }
            }
          }
        }
      }
    },
    "/api/Inventarios/{id}": {
      "get": {
        "tags": [
          "Inventarios"
        ],
        "parameters": [
          {
            "name": "id",
            "in": "path",
            "required": true,
            "schema": {
              "type": "integer",
              "format": "int32"
            }
          }
        ],
        "responses": {
          "200": {
            "description": "OK",
            "content": {
              "text/plain": {
                "schema": {
                  "$ref": "#/components/schemas/Inventario"
                }
              },
              "application/json": {
                "schema": {
                  "$ref": "#/components/schemas/Inventario"
                }
              },
              "text/json": {
                "schema": {
                  "$ref": "#/components/schemas/Inventario"
                }
              }
            }
          }
        }
      },
      "put": {
        "tags": [
          "Inventarios"
        ],
        "parameters": [
          {
            "name": "id",
            "in": "path",
            "required": true,
            "schema": {
              "type": "integer",
              "format": "int32"
            }
          }
        ],
        "requestBody": {
          "content": {
            "application/json": {
              "schema": {
                "$ref": "#/components/schemas/InventarioDTO"
              }
            },
            "text/json": {
              "schema": {
                "$ref": "#/components/schemas/InventarioDTO"
              }
            },
            "application/*+json": {
              "schema": {
                "$ref": "#/components/schemas/InventarioDTO"
              }
            }
          }
        },
        "responses": {
          "200": {
            "description": "OK"
          }
        }
      },
      "delete": {
        "tags": [
          "Inventarios"
        ],
        "parameters": [
          {
            "name": "id",
            "in": "path",
            "required": true,
            "schema": {
              "type": "integer",
              "format": "int32"
            }
          }
        ],
        "responses": {
          "200": {
            "description": "OK"
          }
        }
      }
    },
    "/api/Localidades": {
      "get": {
        "tags": [
          "Localidades"
        ],
        "responses": {
          "200": {
            "description": "OK",
            "content": {
              "text/plain": {
                "schema": {
                  "type": "array",
                  "items": {
                    "$ref": "#/components/schemas/Localidad"
                  }
                }
              },
              "application/json": {
                "schema": {
                  "type": "array",
                  "items": {
                    "$ref": "#/components/schemas/Localidad"
                  }
                }
              },
              "text/json": {
                "schema": {
                  "type": "array",
                  "items": {
                    "$ref": "#/components/schemas/Localidad"
                  }
                }
              }
            }
          }
        }
      },
      "post": {
        "tags": [
          "Localidades"
        ],
        "requestBody": {
          "content": {
            "application/json": {
              "schema": {
                "$ref": "#/components/schemas/Localidad"
              }
            },
            "text/json": {
              "schema": {
                "$ref": "#/components/schemas/Localidad"
              }
            },
            "application/*+json": {
              "schema": {
                "$ref": "#/components/schemas/Localidad"
              }
            }
          }
        },
        "responses": {
          "200": {
            "description": "OK",
            "content": {
              "text/plain": {
                "schema": {
                  "$ref": "#/components/schemas/Localidad"
                }
              },
              "application/json": {
                "schema": {
                  "$ref": "#/components/schemas/Localidad"
                }
              },
              "text/json": {
                "schema": {
                  "$ref": "#/components/schemas/Localidad"
                }
              }
            }
          }
        }
      }
    },
    "/api/Localidades/{id}": {
      "get": {
        "tags": [
          "Localidades"
        ],
        "parameters": [
          {
            "name": "id",
            "in": "path",
            "required": true,
            "schema": {
              "type": "integer",
              "format": "int32"
            }
          }
        ],
        "responses": {
          "200": {
            "description": "OK",
            "content": {
              "text/plain": {
                "schema": {
                  "$ref": "#/components/schemas/Localidad"
                }
              },
              "application/json": {
                "schema": {
                  "$ref": "#/components/schemas/Localidad"
                }
              },
              "text/json": {
                "schema": {
                  "$ref": "#/components/schemas/Localidad"
                }
              }
            }
          }
        }
      },
      "put": {
        "tags": [
          "Localidades"
        ],
        "parameters": [
          {
            "name": "id",
            "in": "path",
            "required": true,
            "schema": {
              "type": "integer",
              "format": "int32"
            }
          }
        ],
        "requestBody": {
          "content": {
            "application/json": {
              "schema": {
                "$ref": "#/components/schemas/Localidad"
              }
            },
            "text/json": {
              "schema": {
                "$ref": "#/components/schemas/Localidad"
              }
            },
            "application/*+json": {
              "schema": {
                "$ref": "#/components/schemas/Localidad"
              }
            }
          }
        },
        "responses": {
          "200": {
            "description": "OK"
          }
        }
      },
      "delete": {
        "tags": [
          "Localidades"
        ],
        "parameters": [
          {
            "name": "id",
            "in": "path",
            "required": true,
            "schema": {
              "type": "integer",
              "format": "int32"
            }
          }
        ],
        "responses": {
          "200": {
            "description": "OK"
          }
        }
      }
    },
    "/api/Miembros": {
      "get": {
        "tags": [
          "Miembros"
        ],
        "responses": {
          "200": {
            "description": "OK",
            "content": {
              "text/plain": {
                "schema": {
                  "type": "array",
                  "items": {
                    "$ref": "#/components/schemas/MiembroDTO"
                  }
                }
              },
              "application/json": {
                "schema": {
                  "type": "array",
                  "items": {
                    "$ref": "#/components/schemas/MiembroDTO"
                  }
                }
              },
              "text/json": {
                "schema": {
                  "type": "array",
                  "items": {
                    "$ref": "#/components/schemas/MiembroDTO"
                  }
                }
              }
            }
          }
        }
      },
      "post": {
        "tags": [
          "Miembros"
        ],
        "requestBody": {
          "content": {
            "application/json": {
              "schema": {
                "$ref": "#/components/schemas/MiembroDTO"
              }
            },
            "text/json": {
              "schema": {
                "$ref": "#/components/schemas/MiembroDTO"
              }
            },
            "application/*+json": {
              "schema": {
                "$ref": "#/components/schemas/MiembroDTO"
              }
            }
          }
        },
        "responses": {
          "200": {
            "description": "OK",
            "content": {
              "text/plain": {
                "schema": {
                  "$ref": "#/components/schemas/MiembroDTO"
                }
              },
              "application/json": {
                "schema": {
                  "$ref": "#/components/schemas/MiembroDTO"
                }
              },
              "text/json": {
                "schema": {
                  "$ref": "#/components/schemas/MiembroDTO"
                }
              }
            }
          }
        }
      }
    },
    "/api/Miembros/{id}": {
      "get": {
        "tags": [
          "Miembros"
        ],
        "parameters": [
          {
            "name": "id",
            "in": "path",
            "required": true,
            "schema": {
              "type": "integer",
              "format": "int32"
            }
          }
        ],
        "responses": {
          "200": {
            "description": "OK",
            "content": {
              "text/plain": {
                "schema": {
                  "$ref": "#/components/schemas/MiembroDTO"
                }
              },
              "application/json": {
                "schema": {
                  "$ref": "#/components/schemas/MiembroDTO"
                }
              },
              "text/json": {
                "schema": {
                  "$ref": "#/components/schemas/MiembroDTO"
                }
              }
            }
          }
        }
      },
      "put": {
        "tags": [
          "Miembros"
        ],
        "parameters": [
          {
            "name": "id",
            "in": "path",
            "required": true,
            "schema": {
              "type": "integer",
              "format": "int32"
            }
          }
        ],
        "requestBody": {
          "content": {
            "application/json": {
              "schema": {
                "$ref": "#/components/schemas/MiembroDTO"
              }
            },
            "text/json": {
              "schema": {
                "$ref": "#/components/schemas/MiembroDTO"
              }
            },
            "application/*+json": {
              "schema": {
                "$ref": "#/components/schemas/MiembroDTO"
              }
            }
          }
        },
        "responses": {
          "200": {
            "description": "OK"
          }
        }
      },
      "delete": {
        "tags": [
          "Miembros"
        ],
        "parameters": [
          {
            "name": "id",
            "in": "path",
            "required": true,
            "schema": {
              "type": "integer",
              "format": "int32"
            }
          }
        ],
        "responses": {
          "200": {
            "description": "OK"
          }
        }
      }
    },
    "/api/Miembros/porLocalidad/{id}": {
      "get": {
        "tags": [
          "Miembros"
        ],
        "parameters": [
          {
            "name": "id",
            "in": "path",
            "required": true,
            "schema": {
              "type": "integer",
              "format": "int32"
            }
          }
        ],
        "responses": {
          "200": {
            "description": "OK",
            "content": {
              "text/plain": {
                "schema": {
                  "type": "array",
                  "items": {
                    "$ref": "#/components/schemas/MiembroDTO"
                  }
                }
              },
              "application/json": {
                "schema": {
                  "type": "array",
                  "items": {
                    "$ref": "#/components/schemas/MiembroDTO"
                  }
                }
              },
              "text/json": {
                "schema": {
                  "type": "array",
                  "items": {
                    "$ref": "#/components/schemas/MiembroDTO"
                  }
                }
              }
            }
          }
        }
      }
    },
    "/api/Movimientos": {
      "get": {
        "tags": [
          "Movimientos"
        ],
        "responses": {
          "200": {
            "description": "OK",
            "content": {
              "text/plain": {
                "schema": {
                  "type": "array",
                  "items": {
                    "$ref": "#/components/schemas/Movimiento"
                  }
                }
              },
              "application/json": {
                "schema": {
                  "type": "array",
                  "items": {
                    "$ref": "#/components/schemas/Movimiento"
                  }
                }
              },
              "text/json": {
                "schema": {
                  "type": "array",
                  "items": {
                    "$ref": "#/components/schemas/Movimiento"
                  }
                }
              }
            }
          }
        }
      },
      "post": {
        "tags": [
          "Movimientos"
        ],
        "requestBody": {
          "content": {
            "application/json": {
              "schema": {
                "$ref": "#/components/schemas/MovimientoDTO"
              }
            },
            "text/json": {
              "schema": {
                "$ref": "#/components/schemas/MovimientoDTO"
              }
            },
            "application/*+json": {
              "schema": {
                "$ref": "#/components/schemas/MovimientoDTO"
              }
            }
          }
        },
        "responses": {
          "200": {
            "description": "OK",
            "content": {
              "text/plain": {
                "schema": {
                  "$ref": "#/components/schemas/Movimiento"
                }
              },
              "application/json": {
                "schema": {
                  "$ref": "#/components/schemas/Movimiento"
                }
              },
              "text/json": {
                "schema": {
                  "$ref": "#/components/schemas/Movimiento"
                }
              }
            }
          }
        }
      }
    },
    "/api/Movimientos/{id}": {
      "get": {
        "tags": [
          "Movimientos"
        ],
        "parameters": [
          {
            "name": "id",
            "in": "path",
            "required": true,
            "schema": {
              "type": "integer",
              "format": "int32"
            }
          }
        ],
        "responses": {
          "200": {
            "description": "OK",
            "content": {
              "text/plain": {
                "schema": {
                  "$ref": "#/components/schemas/Movimiento"
                }
              },
              "application/json": {
                "schema": {
                  "$ref": "#/components/schemas/Movimiento"
                }
              },
              "text/json": {
                "schema": {
                  "$ref": "#/components/schemas/Movimiento"
                }
              }
            }
          }
        }
      },
      "put": {
        "tags": [
          "Movimientos"
        ],
        "parameters": [
          {
            "name": "id",
            "in": "path",
            "required": true,
            "schema": {
              "type": "integer",
              "format": "int32"
            }
          }
        ],
        "requestBody": {
          "content": {
            "application/json": {
              "schema": {
                "$ref": "#/components/schemas/MovimientoDTO"
              }
            },
            "text/json": {
              "schema": {
                "$ref": "#/components/schemas/MovimientoDTO"
              }
            },
            "application/*+json": {
              "schema": {
                "$ref": "#/components/schemas/MovimientoDTO"
              }
            }
          }
        },
        "responses": {
          "200": {
            "description": "OK"
          }
        }
      },
      "delete": {
        "tags": [
          "Movimientos"
        ],
        "parameters": [
          {
            "name": "id",
            "in": "path",
            "required": true,
            "schema": {
              "type": "integer",
              "format": "int32"
            }
          }
        ],
        "responses": {
          "200": {
            "description": "OK"
          }
        }
      }
    },
    "/api/RegistrosSecretaria": {
      "get": {
        "tags": [
          "RegistrosSecretaria"
        ],
        "responses": {
          "200": {
            "description": "OK",
            "content": {
              "text/plain": {
                "schema": {
                  "type": "array",
                  "items": {
                    "$ref": "#/components/schemas/RegistroSecretaria"
                  }
                }
              },
              "application/json": {
                "schema": {
                  "type": "array",
                  "items": {
                    "$ref": "#/components/schemas/RegistroSecretaria"
                  }
                }
              },
              "text/json": {
                "schema": {
                  "type": "array",
                  "items": {
                    "$ref": "#/components/schemas/RegistroSecretaria"
                  }
                }
              }
            }
          }
        }
      },
      "post": {
        "tags": [
          "RegistrosSecretaria"
        ],
        "requestBody": {
          "content": {
            "application/json": {
              "schema": {
                "$ref": "#/components/schemas/RegistroSecretariaDTO"
              }
            },
            "text/json": {
              "schema": {
                "$ref": "#/components/schemas/RegistroSecretariaDTO"
              }
            },
            "application/*+json": {
              "schema": {
                "$ref": "#/components/schemas/RegistroSecretariaDTO"
              }
            }
          }
        },
        "responses": {
          "200": {
            "description": "OK",
            "content": {
              "text/plain": {
                "schema": {
                  "$ref": "#/components/schemas/RegistroSecretaria"
                }
              },
              "application/json": {
                "schema": {
                  "$ref": "#/components/schemas/RegistroSecretaria"
                }
              },
              "text/json": {
                "schema": {
                  "$ref": "#/components/schemas/RegistroSecretaria"
                }
              }
            }
          }
        }
      }
    },
    "/api/RegistrosSecretaria/{id}": {
      "get": {
        "tags": [
          "RegistrosSecretaria"
        ],
        "parameters": [
          {
            "name": "id",
            "in": "path",
            "required": true,
            "schema": {
              "type": "integer",
              "format": "int32"
            }
          }
        ],
        "responses": {
          "200": {
            "description": "OK",
            "content": {
              "text/plain": {
                "schema": {
                  "$ref": "#/components/schemas/RegistroSecretaria"
                }
              },
              "application/json": {
                "schema": {
                  "$ref": "#/components/schemas/RegistroSecretaria"
                }
              },
              "text/json": {
                "schema": {
                  "$ref": "#/components/schemas/RegistroSecretaria"
                }
              }
            }
          }
        }
      },
      "put": {
        "tags": [
          "RegistrosSecretaria"
        ],
        "parameters": [
          {
            "name": "id",
            "in": "path",
            "required": true,
            "schema": {
              "type": "integer",
              "format": "int32"
            }
          }
        ],
        "requestBody": {
          "content": {
            "application/json": {
              "schema": {
                "$ref": "#/components/schemas/RegistroSecretariaDTO"
              }
            },
            "text/json": {
              "schema": {
                "$ref": "#/components/schemas/RegistroSecretariaDTO"
              }
            },
            "application/*+json": {
              "schema": {
                "$ref": "#/components/schemas/RegistroSecretariaDTO"
              }
            }
          }
        },
        "responses": {
          "200": {
            "description": "OK"
          }
        }
      },
      "delete": {
        "tags": [
          "RegistrosSecretaria"
        ],
        "parameters": [
          {
            "name": "id",
            "in": "path",
            "required": true,
            "schema": {
              "type": "integer",
              "format": "int32"
            }
          }
        ],
        "responses": {
          "200": {
            "description": "OK"
          }
        }
      }
    },
    "/api/Usuarios/login": {
      "post": {
        "tags": [
          "Usuarios"
        ],
        "requestBody": {
          "content": {
            "application/json": {
              "schema": {
                "$ref": "#/components/schemas/LoginRequestDTO"
              }
            },
            "text/json": {
              "schema": {
                "$ref": "#/components/schemas/LoginRequestDTO"
              }
            },
            "application/*+json": {
              "schema": {
                "$ref": "#/components/schemas/LoginRequestDTO"
              }
            }
          }
        },
        "responses": {
          "200": {
            "description": "OK",
            "content": {
              "text/plain": {
                "schema": {
                  "$ref": "#/components/schemas/LoginResponseDTO"
                }
              },
              "application/json": {
                "schema": {
                  "$ref": "#/components/schemas/LoginResponseDTO"
                }
              },
              "text/json": {
                "schema": {
                  "$ref": "#/components/schemas/LoginResponseDTO"
                }
              }
            }
          }
        }
      }
    },
    "/api/Usuarios/actual": {
      "get": {
        "tags": [
          "Usuarios"
        ],
        "responses": {
          "200": {
            "description": "OK",
            "content": {
              "text/plain": {
                "schema": {
                  "$ref": "#/components/schemas/UsuarioDTO"
                }
              },
              "application/json": {
                "schema": {
                  "$ref": "#/components/schemas/UsuarioDTO"
                }
              },
              "text/json": {
                "schema": {
                  "$ref": "#/components/schemas/UsuarioDTO"
                }
              }
            }
          }
        }
      }
    }
  },
  "components": {
    "schemas": {
      "ActividadDTO": {
        "type": "object",
        "properties": {
          "fecha": {
            "type": "string",
            "format": "date-time"
          },
          "tipo": {
            "type": "string",
            "nullable": true
          },
          "descripcion": {
            "type": "string",
            "nullable": true
          },
          "localidadId": {
            "type": "integer",
            "format": "int32"
          },
          "nombreLocalidad": {
            "type": "string",
            "nullable": true
          },
          "creadoPorId": {
            "type": "integer",
            "format": "int32",
            "nullable": true
          },
          "creadoPorNombre": {
            "type": "string",
            "nullable": true
          },
          "esGlobal": {
            "type": "boolean"
          }
        },
        "additionalProperties": false
      },
      "Celula": {
        "required": [
          "nombreCelula"
        ],
        "type": "object",
        "properties": {
          "celulaId": {
            "type": "integer",
            "format": "int32"
          },
          "nombreCelula": {
            "maxLength": 100,
            "minLength": 1,
            "type": "string"
          },
          "diaReunion": {
            "maxLength": 50,
            "type": "string",
            "nullable": true
          },
          "horaReunion": {
            "type": "string",
            "format": "date-span",
            "nullable": true
          },
          "liderId": {
            "type": "integer",
            "format": "int32",
            "nullable": true
          },
          "localidadId": {
            "type": "integer",
            "format": "int32"
          },
          "creadoPorID": {
            "type": "integer",
            "format": "int32",
            "nullable": true
          }
        },
        "additionalProperties": false
      },
      "CelulaDTO": {
        "required": [
          "localidadId",
          "nombreCelula"
        ],
        "type": "object",
        "properties": {
          "nombreCelula": {
            "maxLength": 100,
            "minLength": 1,
            "type": "string"
          },
          "diaReunion": {
            "maxLength": 50,
            "type": "string",
            "nullable": true
          },
          "horaReunion": {
            "type": "string",
            "format": "date-span",
            "nullable": true
          },
          "liderId": {
            "type": "integer",
            "format": "int32",
            "nullable": true
          },
          "localidadId": {
            "type": "integer",
            "format": "int32"
          },
          "nombreLocalidad": {
            "type": "string",
            "nullable": true
          },
          "nombreLider": {
            "type": "string",
            "nullable": true
          },
          "creadoPorId": {
            "type": "integer",
            "format": "int32",
            "nullable": true
          },
          "creadoPorNombre": {
            "type": "string",
            "nullable": true
          },
          "esGlobal": {
            "type": "boolean"
          }
        },
        "additionalProperties": false
      },
      "Cuenta": {
        "required": [
          "nombreCuenta",
          "tipo"
        ],
        "type": "object",
        "properties": {
          "cuentaId": {
            "type": "integer",
            "format": "int32"
          },
          "nombreCuenta": {
            "maxLength": 100,
            "minLength": 1,
            "type": "string"
          },
          "tipo": {
            "maxLength": 50,
            "minLength": 1,
            "type": "string"
          },
          "saldo": {
            "type": "number",
            "format": "double"
          },
          "localidadId": {
            "type": "integer",
            "format": "int32"
          },
          "creadoPorID": {
            "type": "integer",
            "format": "int32",
            "nullable": true
          }
        },
        "additionalProperties": false
      },
      "CuentaDTO": {
        "required": [
          "localidadId",
          "nombreCuenta",
          "tipo"
        ],
        "type": "object",
        "properties": {
          "nombreCuenta": {
            "maxLength": 100,
            "minLength": 1,
            "type": "string"
          },
          "tipo": {
            "maxLength": 50,
            "minLength": 1,
            "type": "string"
          },
          "descripcion": {
            "maxLength": 500,
            "type": "string",
            "nullable": true
          },
          "localidadId": {
            "type": "integer",
            "format": "int32"
          },
          "nombreLocalidad": {
            "type": "string",
            "nullable": true
          },
          "creadoPorId": {
            "type": "integer",
            "format": "int32",
            "nullable": true
          },
          "creadoPorNombre": {
            "type": "string",
            "nullable": true
          },
          "esGlobal": {
            "type": "boolean"
          }
        },
        "additionalProperties": false
      },
      "DashboardDTO": {
        "type": "object",
        "properties": {
          "miembrosActivos": {
            "type": "integer",
            "format": "int32"
          },
          "nuevosMes": {
            "type": "integer",
            "format": "int32"
          },
          "celulas": {
            "type": "integer",
            "format": "int32"
          },
          "ofrendasMensuales": {
            "type": "number",
            "format": "double"
          },
          "inventarioTotal": {
            "type": "integer",
            "format": "int32"
          },
          "balanceFinanzas": {
            "type": "number",
            "format": "double"
          },
          "cumpleaniosHoy": {
            "type": "integer",
            "format": "int32"
          },
          "alertas": {
            "type": "integer",
            "format": "int32"
          },
          "eventosProximos": {
            "type": "integer",
            "format": "int32"
          },
          "actividadReciente": {
            "type": "integer",
            "format": "int32"
          },
          "localidadId": {
            "type": "integer",
            "format": "int32"
          },
          "nombreLocalidad": {
            "type": "string",
            "nullable": true
          },
          "esGlobal": {
            "type": "boolean"
          }
        },
        "additionalProperties": false
      },
      "EventoImportanteDTO": {
        "type": "object",
        "properties": {
          "titulo": {
            "type": "string",
            "nullable": true
          },
          "fecha": {
            "type": "string",
            "format": "date-time"
          },
          "hora": {
            "type": "string",
            "format": "date-span"
          },
          "localidadId": {
            "type": "integer",
            "format": "int32"
          },
          "nombreLocalidad": {
            "type": "string",
            "nullable": true
          },
          "creadoPorId": {
            "type": "integer",
            "format": "int32",
            "nullable": true
          },
          "creadoPorNombre": {
            "type": "string",
            "nullable": true
          },
          "esGlobal": {
            "type": "boolean"
          }
        },
        "additionalProperties": false
      },
      "Inventario": {
        "required": [
          "nombreArticulo"
        ],
        "type": "object",
        "properties": {
          "inventarioId": {
            "type": "integer",
            "format": "int32"
          },
          "nombreArticulo": {
            "maxLength": 150,
            "minLength": 1,
            "type": "string"
          },
          "cantidad": {
            "type": "integer",
            "format": "int32"
          },
          "ubicacion": {
            "maxLength": 100,
            "type": "string",
            "nullable": true
          },
          "localidadId": {
            "type": "integer",
            "format": "int32"
          },
          "creadoPorID": {
            "type": "integer",
            "format": "int32",
            "nullable": true
          }
        },
        "additionalProperties": false
      },
      "InventarioDTO": {
        "required": [
          "cantidad",
          "localidadId",
          "nombreArticulo"
        ],
        "type": "object",
        "properties": {
          "nombreArticulo": {
            "maxLength": 150,
            "minLength": 1,
            "type": "string"
          },
          "cantidad": {
            "maximum": 2147483647,
            "minimum": 1,
            "type": "integer",
            "format": "int32"
          },
          "ubicacion": {
            "maxLength": 100,
            "type": "string",
            "nullable": true
          },
          "localidadId": {
            "type": "integer",
            "format": "int32"
          },
          "nombreLocalidad": {
            "type": "string",
            "nullable": true
          },
          "creadoPorId": {
            "type": "integer",
            "format": "int32",
            "nullable": true
          },
          "creadoPorNombre": {
            "type": "string",
            "nullable": true
          },
          "esGlobal": {
            "type": "boolean"
          }
        },
        "additionalProperties": false
      },
      "Localidad": {
        "required": [
          "nombreLocalidad"
        ],
        "type": "object",
        "properties": {
          "localidadId": {
            "type": "integer",
            "format": "int32"
          },
          "nombreLocalidad": {
            "maxLength": 100,
            "minLength": 1,
            "type": "string"
          },
          "direccion": {
            "maxLength": 255,
            "type": "string",
            "nullable": true
          },
          "fechaFundacion": {
            "type": "string",
            "format": "date-time",
            "nullable": true
          }
        },
        "additionalProperties": false
      },
      "LocalidadResumenDTO": {
        "type": "object",
        "properties": {
          "id": {
            "type": "integer",
            "format": "int32"
          },
          "nombreLocalidad": {
            "type": "string",
            "nullable": true
          }
        },
        "additionalProperties": false
      },
      "LoginRequest": {
        "type": "object",
        "properties": {
          "username": {
            "type": "string",
            "nullable": true
          },
          "password": {
            "type": "string",
            "nullable": true
          }
        },
        "additionalProperties": false
      },
      "LoginRequestDTO": {
        "required": [
          "email",
          "password"
        ],
        "type": "object",
        "properties": {
          "email": {
            "minLength": 1,
            "type": "string",
            "format": "email"
          },
          "password": {
            "minLength": 6,
            "type": "string"
          },
          "localidadId": {
            "type": "integer",
            "format": "int32",
            "nullable": true
          },
          "recordarSesion": {
            "type": "boolean"
          }
        },
        "additionalProperties": false
      },
      "LoginResponseDTO": {
        "type": "object",
        "properties": {
          "token": {
            "type": "string",
            "nullable": true
          },
          "usuario": {
            "$ref": "#/components/schemas/UsuarioDTO"
          },
          "esAdmin": {
            "type": "boolean",
            "readOnly": true
          },
          "localidadActual": {
            "type": "string",
            "nullable": true,
            "readOnly": true
          },
          "puedeVerTodasLocalidades": {
            "type": "boolean",
            "readOnly": true
          }
        },
        "additionalProperties": false
      },
      "MiembroDTO": {
        "type": "object",
        "properties": {
          "miembroId": {
            "type": "integer",
            "format": "int32"
          },
          "noRegistro": {
            "type": "string",
            "nullable": true
          },
          "localidadId": {
            "type": "integer",
            "format": "int32"
          },
          "nombreLocalidad": {
            "type": "string",
            "nullable": true
          },
          "fechaBautizado": {
            "type": "string",
            "format": "date-time",
            "nullable": true
          },
          "nombreCompleto": {
            "type": "string",
            "nullable": true
          },
          "fechaNacimiento": {
            "type": "string",
            "format": "date-time",
            "nullable": true
          },
          "lugar": {
            "type": "string",
            "nullable": true
          },
          "direccion": {
            "type": "string",
            "nullable": true
          },
          "telefono": {
            "type": "string",
            "nullable": true
          },
          "provincia": {
            "type": "string",
            "nullable": true
          },
          "ciudad": {
            "type": "string",
            "nullable": true
          },
          "nacionalidad": {
            "type": "string",
            "nullable": true
          },
          "sexo": {
            "type": "string",
            "nullable": true
          },
          "estadoCivil": {
            "type": "string",
            "nullable": true
          },
          "correo": {
            "type": "string",
            "nullable": true
          },
          "tipoDocumento": {
            "type": "string",
            "nullable": true
          },
          "numeroDoc": {
            "type": "string",
            "nullable": true
          },
          "nivelAcademico": {
            "type": "string",
            "nullable": true
          },
          "profesion": {
            "type": "string",
            "nullable": true
          },
          "conyugue": {
            "type": "string",
            "nullable": true
          },
          "madre": {
            "type": "string",
            "nullable": true
          },
          "padre": {
            "type": "string",
            "nullable": true
          },
          "hijos": {
            "type": "string",
            "nullable": true
          },
          "esGlobal": {
            "type": "boolean"
          }
        },
        "additionalProperties": false
      },
      "Movimiento": {
        "required": [
          "fechaMovimiento",
          "monto",
          "tipoMovimiento"
        ],
        "type": "object",
        "properties": {
          "movimientoId": {
            "type": "integer",
            "format": "int32"
          },
          "fechaMovimiento": {
            "type": "string",
            "format": "date-time"
          },
          "monto": {
            "type": "number",
            "format": "double"
          },
          "tipoMovimiento": {
            "maxLength": 50,
            "minLength": 1,
            "type": "string"
          },
          "descripcion": {
            "maxLength": 500,
            "type": "string",
            "nullable": true
          },
          "localidadId": {
            "type": "integer",
            "format": "int32"
          },
          "cuentaId": {
            "type": "integer",
            "format": "int32"
          },
          "creadoPorID": {
            "type": "integer",
            "format": "int32",
            "nullable": true
          }
        },
        "additionalProperties": false
      },
      "MovimientoDTO": {
        "required": [
          "fechaMovimiento",
          "localidadID",
          "monto",
          "tipoMovimiento"
        ],
        "type": "object",
        "properties": {
          "fechaMovimiento": {
            "type": "string",
            "format": "date-time"
          },
          "monto": {
            "maximum": 1000000000,
            "minimum": 0.01,
            "type": "number",
            "format": "double"
          },
          "tipoMovimiento": {
            "maxLength": 50,
            "minLength": 1,
            "type": "string"
          },
          "descripcion": {
            "maxLength": 500,
            "type": "string",
            "nullable": true
          },
          "localidadID": {
            "type": "integer",
            "format": "int32"
          },
          "localidadNombre": {
            "type": "string",
            "nullable": true
          },
          "cuentaID": {
            "type": "integer",
            "format": "int32"
          },
          "nombreCuenta": {
            "type": "string",
            "nullable": true
          },
          "creadoPorID": {
            "type": "integer",
            "format": "int32",
            "nullable": true
          },
          "creadoPorNombre": {
            "type": "string",
            "nullable": true
          },
          "esGlobal": {
            "type": "boolean"
          }
        },
        "additionalProperties": false
      },
      "RegistroSecretaria": {
        "required": [
          "fechaRegistro",
          "tipoRegistro",
          "titulo"
        ],
        "type": "object",
        "properties": {
          "registroId": {
            "type": "integer",
            "format": "int32"
          },
          "fechaRegistro": {
            "type": "string",
            "format": "date-time"
          },
          "tipoRegistro": {
            "maxLength": 50,
            "minLength": 1,
            "type": "string"
          },
          "titulo": {
            "maxLength": 200,
            "minLength": 1,
            "type": "string"
          },
          "descripcion": {
            "type": "string",
            "nullable": true
          },
          "documentoUrl": {
            "maxLength": 500,
            "type": "string",
            "nullable": true
          },
          "localidadId": {
            "type": "integer",
            "format": "int32"
          },
          "creadoPorId": {
            "type": "integer",
            "format": "int32",
            "nullable": true
          }
        },
        "additionalProperties": false
      },
      "RegistroSecretariaDTO": {
        "required": [
          "fechaRegistro",
          "tipoRegistro",
          "titulo"
        ],
        "type": "object",
        "properties": {
          "fechaRegistro": {
            "type": "string",
            "format": "date-time"
          },
          "tipoRegistro": {
            "maxLength": 50,
            "minLength": 1,
            "type": "string"
          },
          "titulo": {
            "maxLength": 200,
            "minLength": 1,
            "type": "string"
          },
          "descripcion": {
            "type": "string",
            "nullable": true
          },
          "documentoURL": {
            "maxLength": 500,
            "type": "string",
            "nullable": true
          },
          "localidadID": {
            "type": "integer",
            "format": "int32"
          },
          "localidadNombre": {
            "type": "string",
            "nullable": true
          },
          "creadoPorID": {
            "type": "integer",
            "format": "int32",
            "nullable": true
          },
          "creadoPorNombre": {
            "type": "string",
            "nullable": true
          },
          "esGlobal": {
            "type": "boolean"
          }
        },
        "additionalProperties": false
      },
      "TendenciaDTO": {
        "type": "object",
        "properties": {
          "meses": {
            "type": "array",
            "items": {
              "type": "string"
            },
            "nullable": true
          },
          "nuevosMiembros": {
            "type": "array",
            "items": {
              "type": "integer",
              "format": "int32"
            },
            "nullable": true
          },
          "bautismos": {
            "type": "array",
            "items": {
              "type": "integer",
              "format": "int32"
            },
            "nullable": true
          },
          "ingresos": {
            "type": "array",
            "items": {
              "type": "number",
              "format": "double"
            },
            "nullable": true
          },
          "egresos": {
            "type": "array",
            "items": {
              "type": "number",
              "format": "double"
            },
            "nullable": true
          },
          "localidadID": {
            "type": "integer",
            "format": "int32"
          },
          "localidadNombre": {
            "type": "string",
            "nullable": true
          },
          "esGlobal": {
            "type": "boolean"
          }
        },
        "additionalProperties": false
      },
      "UsuarioDTO": {
        "type": "object",
        "properties": {
          "usuarioID": {
            "type": "integer",
            "format": "int32"
          },
          "nombreUsuario": {
            "type": "string",
            "nullable": true
          },
          "email": {
            "type": "string",
            "nullable": true
          },
          "rol": {
            "type": "string",
            "nullable": true
          },
          "localidadID": {
            "type": "integer",
            "format": "int32"
          },
          "miembroID": {
            "type": "integer",
            "format": "int32",
            "nullable": true
          },
          "localidadesDisponibles": {
            "type": "array",
            "items": {
              "$ref": "#/components/schemas/LocalidadResumenDTO"
            },
            "nullable": true
          },
          "esAdmin": {
            "type": "boolean"
          },
          "localidadNombre": {
            "type": "string",
            "nullable": true
          },
          "puedeVerTodasLocalidades": {
            "type": "boolean",
            "readOnly": true
          }
        },
        "additionalProperties": false
      }
    }
  },
  "tags": [
    {
      "name": "Auth"
    },
    {
      "name": "Celulas"
    },
    {
      "name": "Cuentas"
    },
    {
      "name": "Dashboard"
    },
    {
      "name": "Inventarios"
    },
    {
      "name": "Localidades"
    },
    {
      "name": "Miembros"
    },
    {
      "name": "Movimientos"
    },
    {
      "name": "RegistrosSecretaria"
    },
    {
      "name": "Usuarios"
    }
  ]
}